Workbook

Sheet Dashboard
A1: MotorPH Analytical Dashboard
A2: Product lineup and sales performance | Sales records 13 Jan 2025 to 31 Aug 2025 | Amounts in Philippine pesos (₱)
A4: MotorPH Overview
A5: Total Revenue | D5: Total Units Sold | G5: Sales Orders | J5: Average Order Value | M5: Product Records | P5: Average Unit Price
A6: =SUM('Sales Data'!$F$2:$F$995) -> 4459496800 | D6: =SUM('Sales Data'!$E$2:$E$995) -> 17619 | G6: =COUNTA('Sales Data'!$C$2:$C$995) -> 994 | J6: =SUM('Sales Data'!$F$2:$F$995)/COUNTA('Sales Data'!$C$2:$C$995) -> 4486415.3 | M6: =COUNTA(Products!$B$2:$B$51) -> 50 | P6: =AVERAGE(Products!$D$2:$D$51) -> 257872
A7: all sales orders | D7: all sales orders | G7: rows in Sales Data | J7: revenue per order | M7: catalogue rows, not stock | P7: across catalogue
A9: Sales Performance
A44: Sales by Product Category
A67: Key Insights (generated from the data when the workbook was built)
A68: • Scooter is the top revenue category: ₱747.2M (16.8% of sales) from 12 of 50 models (24% of the catalogue).
A69: • The top 3 categories (Scooter, Cruiser, Naked Bike) bring in 44% of revenue, so sales are concentrated in a few segments.
A70: • Heritage earns the most per model (₱276.6M per product), which means the number of models in a category does not by itself predict sales.
A71: • Best seller by revenue: Moto Guzzi V7 Stone (₱327.3M). Best seller by units: Bristol Bobber 650 (575 units).
A72: • Retail orders contribute 53.5% of revenue and wholesale 45.7%, so both channels drive sales (0.8% of revenue has client type 'Unknown' in the source data).
A73: • Data coverage: sales run from 13 Jan 2025 to 31 Aug 2025, with no sales records for Feb 2025, Mar 2025, Apr 2025, May 2025 and only a handful of records in Jan 2025. Trend conclusions should be drawn from the months with full data.
A75: What the Data Can and Cannot Show
A76: • What the counts mean: 'Product Records per Category' counts catalogue records (one row per model, N = 50). It is not stock on hand. The files contain no stock-quantity field, so the Inventory Section shows products, categories, prices and sales, not quantities left.
A77: • Variety is not demand: 7 of 17 categories have only one model, so their share rests on a single product. Revenue per model compares sales between categories but cannot show whether a category is over- or under-stocked.
... A81: Inventory Section: Product Catalogue, Pricing and Sales (no stock-on-hand data)
A82: ID | B82: Product Name | E82: Category | G82: Unit Price | I82: Mfg Year | J82: Acquired | K82: Units Sold | L82: Revenue
A83: =Products!A2 -> 37 | B83: =Products!B2 -> Moto Morini X-Cape 650 | E83: =Products!C2 -> Adventure | G83: =Products!D2 -> 369000 | I83: =Products!E2 -> 2023 | J83: =Products!F2 -> 2024 | K83: =Products!G2 -> 297 | L83: =Products!H2 -> 109593000
A84: =Products!A3 -> 15 | B84: =Products!B3 -> BMW G 310 GS | E84: =Products!C3 -> Adventure | G84: =Products!D3 -> 320000 | I84: =Products!E3 -> 2023 | J84: =Products!F3 -> 2024 | K84: =Products!G3 -> 426 | L84: =Products!H3 -> 136320000
A85: =Products!A4 -> 33 | B85: =Products!B4 -> Zontes 310X | E85: =Products!C4 -> Adventure | G85: =Products!D4 -> 248000 | I85: =Products!E4 -> 2023 | J85: =Products!F4 -> 2024 | K85: =Products!G4 -> 480 | L85: =Products!H4 -> 119040000
A86: =Products!A5 -> 24 | B86: =Products!B5 -> Motorstar Xplorer 250R | E86: =Products!C5 -> Adventure | G86: =Products!D5 -> 78900 | I86: =Products!E5 -> 2020 | J86: =Products!F5 -> 2021 | K86: =Products!G5 -> 353 | L86: =Products!H5 -> 27851700
A87: =Products!A6 -> 7 | B87: =Products!B6 -> Bristol Veloce 500 | E87: =Products!C6 -> Cafe Racer | G87: =Products!D6 -> 328000 | I87: =Products!E6 -> 2022 | J87: =Products!F6 -> 2023 | K87: =Products!G6 -> 230 | L87: =Products!H6 -> 75440000
A88: =Products!A7 -> 48 | B88: =Products!B7 -> Zontes GK350 | E88: =Products!C7 -> Cafe Racer | G88: =Products!D7 -> 269000 | I88: =Products!E7 -> 2023 | J88: =Products!F7 -> 2024 | K88: =Products!G7 -> 348 | L88: =Products!H7 -> 93612000
A89: =Products!A8 -> 5 | B89: =Products!B8 -> Royal Enfield Classic 350 | E89: =Products!C8 -> Classic | G89: =Products!D8 -> 250000 | I89: =Products!E8 -> 2022 | J89: =Products!F8 -> 2023 | K89: =Products!G8 -> 458 | L89: =Products!H8 -> 114500000
A90: =Products!A9 -> 28 | B90: =Products!B9 -> Bajaj CT125 | E90: =Products!C9 -> Commuter | G90: =Products!D9 -> 67900 | I90: =Products!E9 -> 2021 | J90: =Products!F9 -> 2022 | K90: =Products!G9 -> 509 | L90: =Products!H9 -> 34561100
A91: =Products!A10 -> 30 | B91: =Products!B10 -> Rusi Flash 125 | E91: =Products!C10 -> Commuter | G91: =Products!D10 -> 48000 | I91: =Products!E10 -> 2020 | J91: =Products!F10 -> 2021 | K91: =Products!G10 -> 393 | L91: =Products!H10 -> 18864000
A92: =Products!A11 -> 42 | B92: =Products!B11 -> Honda Rebel 1100 | E92: =Products!C11 -> Cruiser | G92: =Products!D11 -> 650000 | I92: =Products!E11 -> 2023 | J92: =Products!F11 -> 2024 | K92: =Products!G11 -> 256 | L92: =Products!H11 -> 166400000
A93: =Products!A12 -> 32 | B93: =Products!B12 -> Harley-Davidson Street 750 | E93: =Products!C12 -> Cruiser | G93: =Products!D12 -> 499000 | I93: =Products!E12 -> 2020 | J93: =Products!F12 -> 2021 | K93: =Products!G12 -> 212 | L93: =Products!H12 -> 105788000
A94: =Products!A13 -> 22 | B94: =Products!B13 -> Bristol Bobber 650 | E94: =Products!C13 -> Cruiser | G94: =Products!D13 -> 398000 | I94: =Products!E13 -> 2022 | J94: =Products!F13 -> 2023 | K94: =Products!G13 -> 575 | L94: =Products!H13 -> 228850000
... A132: =Products!A51 -> 50 | B132: =Products!B51 -> SYM Husky 150 | E132: =Products!C51 -> Underbone | G132: =Products!D51 -> 72900 | I132: =Products!E51 -> 2022 | J132: =Products!F51 -> 2023 | K132: =Products!G51 -> 190 | L132: =Products!H51 -> 13851000

Sheet Summary Tables
A1: Summary Tables (all values are formulas on the Sales Data and Products sheets)
A3: Monthly revenue | E3: Revenue by client type | I3: Revenue by payment method | M3: Top 10 products by revenue | Q3: Top 10 products by units sold
A4: Month | B4: Revenue | C4: Units | E4: Client Type | F4: Revenue | G4: Share | I4: Payment Method | J4: Revenue | K4: Share | M4: Product | N4: Revenue | O4: Units | Q4: Product | R4: Revenue | S4: Units
A5: 45658 | B5: =SUMIFS('Sales Data'!$F$2:$F$995,'Sales Data'!$A$2:$A$995,">="&A5,'Sales Data'!$A$2:$A$995,"<"&EDATE(A5,1)) -> 1425900 | C5: =SUMIFS('Sales Data'!$E$2:$E$995,'Sales Data'!$A$2:$A$995,">="&A5,'Sales Data'!$A$2:$A$995,"<"&EDATE(A5,1)) -> 21 | E5: Retail | F5: =SUMIFS('Sales Data'!$F$2:$F$995,'Sales Data'!$B$2:$B$995,E5) -> 2387945300 | G5: =F5/SUM(F$5:F$7) -> 0.53547416 | I5: Credit Card | J5: =SUMIFS('Sales Data'!$F$2:$F$995,'Sales Data'!$G$2:$G$995,I5) -> 1569820600 | K5: =J5/SUM(J$5:J$8) -> 0.35201743 | M5: Moto Guzzi V7 Stone | N5: =SUMIFS('Sales Data'!$F$2:$F$995,'Sales Data'!$C$2:$C$995,M5) -> 327275000 | O5: =SUMIFS('Sales Data'!$E$2:$E$995,'Sales Data'!$C$2:$C$995,M5) -> 475 | Q5: Bristol Bobber 650 | R5: =SUMIFS('Sales Data'!$F$2:$F$995,'Sales Data'!$C$2:$C$995,Q5) -> 228850000 | S5: =SUMIFS('Sales Data'!$E$2:$E$995,'Sales Data'!$C$2:$C$995,Q5) -> 575
A6: 45689 | B6: =SUMIFS('Sales Data'!$F$2:$F$995,'Sales Data'!$A$2:$A$995,">="&A6,'Sales Data'!$A$2:$A$995,"<"&EDATE(A6,1)) -> 0 | C6: =SUMIFS('Sales Data'!$E$2:$E$995,'Sales Data'!$A$2:$A$995,">="&A6,'Sales Data'!$A$2:$A$995,"<"&EDATE(A6,1)) -> 0 | E6: Wholesale | F6: =SUMIFS('Sales Data'!$F$2:$F$995,'Sales Data'!$B$2:$B$995,E6) -> 2036324900 | G6: =F6/SUM(F$5:F$7) -> 0.45662661 | I6: Transfer | J6: =SUMIFS('Sales Data'!$F$2:$F$995,'Sales Data'!$G$2:$G$995,I6) -> 1431534300 | K6: =J6/SUM(J$5:J$8) -> 0.32100803 | M6: Bristol Bobber 650 | N6: =SUMIFS('Sales Data'!$F$2:$F$995,'Sales Data'!$C$2:$C$995,M6) -> 228850000 | O6: =SUMIFS('Sales Data'!$E$2:$E$995,'Sales Data'!$C$2:$C$995,M6) -> 575 | Q6: Bajaj CT125 | R6: =SUMIFS('Sales Data'!$F$2:$F$995,'Sales Data'!$C$2:$C$995,Q6) -> 34561100 | S6: =SUMIFS('Sales Data'!$E$2:$E$995,'Sales Data'!$C$2:$C$995,Q6) -> 509
A7: 45717 | B7: =SUMIFS('Sales Data'!$F$2:$F$995,'Sales Data'!$A$2:$A$995,">="&A7,'Sales Data'!$A$2:$A$995,"<"&EDATE(A7,1)) -> 0 | C7: =SUMIFS('Sales Data'!$E$2:$E$995,'Sales Data'!$A$2:$A$995,">="&A7,'Sales Data'!$A$2:$A$995,"<"&EDATE(A7,1)) -> 0 | E7: Unknown | F7: =SUMIFS('Sales Data'!$F$2:$F$995,'Sales Data'!$B$2:$B$995,E7) -> 35226600 | G7: =F7/SUM(F$5:F$7) -> 0.007899232 | I7: Cash | J7: =SUMIFS('Sales Data'!$F$2:$F$995,'Sales Data'!$G$2:$G$995,I7) -> 1427338800 | K7: =J7/SUM(J$5:J$8) -> 0.32006723 | M7: BMW R nineT | N7: =SUMIFS('Sales Data'!$F$2:$F$995,'Sales Data'!$C$2:$C$995,M7) -> 225865000 | O7: =SUMIFS('Sales Data'!$E$2:$E$995,'Sales Data'!$C$2:$C$995,M7) -> 227 | Q7: CFMoto 300SR | R7: =SUMIFS('Sales Data'!$F$2:$F$995,'Sales Data'!$C$2:$C$995,Q7) -> 81840000 | S7: =SUMIFS('Sales Data'!$E$2:$E$995,'Sales Data'!$C$2:$C$995,Q7) -> 496
A8: 45748 | B8: =SUMIFS('Sales Data'!$F$2:$F$995,'Sales Data'!$A$2:$A$995,">="&A8,'Sales Data'!$A$2:$A$995,"<"&EDATE(A8,1)) -> 0 | C8: =SUMIFS('Sales Data'!$E$2:$E$995,'Sales Data'!$A$2:$A$995,">="&A8,'Sales Data'!$A$2:$A$995,"<"&EDATE(A8,1)) -> 0 | I8: Unknown | J8: =SUMIFS('Sales Data'!$F$2:$F$995,'Sales Data'!$G$2:$G$995,I8) -> 30803100 | K8: =J8/SUM(J$5:J$8) -> 0.006907304 | M8: KTM 790 Duke | N8: =SUMIFS('Sales Data'!$F$2:$F$995,'Sales Data'!$C$2:$C$995,M8) -> 217437000 | O8: =SUMIFS('Sales Data'!$E$2:$E$995,'Sales Data'!$C$2:$C$995,M8) -> 363 | Q8: Yamaha Serow 250 | R8: =SUMIFS('Sales Data'!$F$2:$F$995,'Sales Data'!$C$2:$C$995,Q8) -> 148304000 | S8: =SUMIFS('Sales Data'!$E$2:$E$995,'Sales Data'!$C$2:$C$995,Q8) -> 496
A9: 45778 | B9: =SUMIFS('Sales Data'!$F$2:$F$995,'Sales Data'!$A$2:$A$995,">="&A9,'Sales Data'!$A$2:$A$995,"<"&EDATE(A9,1)) -> 0 | C9: =SUMIFS('Sales Data'!$E$2:$E$995,'Sales Data'!$A$2:$A$995,">="&A9,'Sales Data'!$A$2:$A$995,"<"&EDATE(A9,1)) -> 0 | M9: Honda Rebel 1100 | N9: =SUMIFS('Sales Data'!$F$2:$F$995,'Sales Data'!$C$2:$C$995,M9) -> 166400000 | O9: =SUMIFS('Sales Data'!$E$2:$E$995,'Sales Data'!$C$2:$C$995,M9) -> 256 | Q9: Yamaha FZi 150 | R9: =SUMIFS('Sales Data'!$F$2:$F$995,'Sales Data'!$C$2:$C$995,Q9) -> 48151800 | S9: =SUMIFS('Sales Data'!$E$2:$E$995,'Sales Data'!$C$2:$C$995,Q9) -> 482
A10: 45809 | B10: =SUMIFS('Sales Data'!$F$2:$F$995,'Sales Data'!$A$2:$A$995,">="&A10,'Sales Data'!$A$2:$A$995,"<"&EDATE(A10,1)) -> 1522120700 | C10: =SUMIFS('Sales Data'!$E$2:$E$995,'Sales Data'!$A$2:$A$995,">="&A10,'Sales Data'!$A$2:$A$995,"<"&EDATE(A10,1)) -> 6095 | M10: Yamaha Serow 250 | N10: =SUMIFS('Sales Data'!$F$2:$F$995,'Sales Data'!$C$2:$C$995,M10) -> 148304000 | O10: =SUMIFS('Sales Data'!$E$2:$E$995,'Sales Data'!$C$2:$C$995,M10) -> 496 | Q10: Zontes 310X | R10: =SUMIFS('Sales Data'!$F$2:$F$995,'Sales Data'!$C$2:$C$995,Q10) -> 119040000 | S10: =SUMIFS('Sales Data'!$E$2:$E$995,'Sales Data'!$C$2:$C$995,Q10) -> 480
A11: 45839 | B11: =SUMIFS('Sales Data'!$F$2:$F$995,'Sales Data'!$A$2:$A$995,">="&A11,'Sales Data'!$A$2:$A$995,"<"&EDATE(A11,1)) -> 1490582700 | C11: =SUMIFS('Sales Data'!$E$2:$E$995,'Sales Data'!$A$2:$A$995,">="&A11,'Sales Data'!$A$2:$A$995,"<"&EDATE(A11,1)) -> 5845 | M11: CFMoto 650MT | N11: =SUMIFS('Sales Data'!$F$2:$F$995,'Sales Data'!$C$2:$C$995,M11) -> 147315000 | O11: =SUMIFS('Sales Data'!$E$2:$E$995,'Sales Data'!$C$2:$C$995,M11) -> 427 | Q11: Moto Guzzi V7 Stone | R11: =SUMIFS('Sales Data'!$F$2:$F$995,'Sales Data'!$C$2:$C$995,Q11) -> 327275000 | S11: =SUMIFS('Sales Data'!$E$2:$E$995,'Sales Data'!$C$2:$C$995,Q11) -> 475
A12: 45870 | B12: =SUMIFS('Sales Data'!$F$2:$F$995,'Sales Data'!$A$2:$A$995,">="&A12,'Sales Data'!$A$2:$A$995,"<"&EDATE(A12,1)) -> 1445367500 | C12: =SUMIFS('Sales Data'!$E$2:$E$995,'Sales Data'!$A$2:$A$995,">="&A12,'Sales Data'!$A$2:$A$995,"<"&EDATE(A12,1)) -> 5658 | M12: Vespa GTS Super 300 | N12: =SUMIFS('Sales Data'!$F$2:$F$995,'Sales Data'!$C$2:$C$995,M12) -> 144474000 | O12: =SUMIFS('Sales Data'!$E$2:$E$995,'Sales Data'!$C$2:$C$995,M12) -> 363 | Q12: Royal Enfield Classic 350 | R12: =SUMIFS('Sales Data'!$F$2:$F$995,'Sales Data'!$C$2:$C$995,Q12) -> 114500000 | S12: =SUMIFS('Sales Data'!$E$2:$E$995,'Sales Data'!$C$2:$C$995,Q12) -> 458
M13: Honda CBR500R | N13: =SUMIFS('Sales Data'!$F$2:$F$995,'Sales Data'!$C$2:$C$995,M13) -> 143541000 | O13: =SUMIFS('Sales Data'!$E$2:$E$995,'Sales Data'!$C$2:$C$995,M13) -> 369 | Q13: Honda ADV 160 | R13: =SUMIFS('Sales Data'!$F$2:$F$995,'Sales Data'!$C$2:$C$995,Q13) -> 75359300 | S13: =SUMIFS('Sales Data'!$E$2:$E$995,'Sales Data'!$C$2:$C$995,Q13) -> 457
M14: BMW G 310 GS | N14: =SUMIFS('Sales Data'!$F$2:$F$995,'Sales Data'!$C$2:$C$995,M14) -> 136320000 | O14: =SUMIFS('Sales Data'!$E$2:$E$995,'Sales Data'!$C$2:$C$995,M14) -> 426 | Q14: CFMoto 300NK | R14: =SUMIFS('Sales Data'!$F$2:$F$995,'Sales Data'!$C$2:$C$995,Q14) -> 70620000 | S14: =SUMIFS('Sales Data'!$E$2:$E$995,'Sales Data'!$C$2:$C$995,Q14) -> 428
A20: Product records per category (Milestone 2 Draft chart) | E20: Category sales performance
A21: Category | B21: Products | C21: % of catalogue | E21: Category | F21: Products | G21: Units Sold | H21: Revenue | I21: Revenue Share | J21: Revenue per Model
A22: Scooter | B22: =COUNTIF(Products!$C$2:$C$51,A22) -> 12 | C22: =B22/SUM(B$22:B$38) -> 0.24 | E22: Scooter | F22: =COUNTIF(Products!$C$2:$C$51,E22) -> 12 | G22: =SUMIFS('Sales Data'!$E$2:$E$995,'Sales Data'!$H$2:$H$995,E22) -> 4056 | H22: =SUMIFS('Sales Data'!$F$2:$F$995,'Sales Data'!$H$2:$H$995,E22) -> 747176900 | I22: =H22/SUM(H$22:H$38) -> 0.16754736 | J22: =IFERROR(H22/F22,0) -> 62264742
A23: Naked Bike | B23: =COUNTIF(Products!$C$2:$C$51,A23) -> 7 | C23: =B23/SUM(B$22:B$38) -> 0.14 | E23: Cruiser | F23: =COUNTIF(Products!$C$2:$C$51,E23) -> 4 | G23: =SUMIFS('Sales Data'!$E$2:$E$995,'Sales Data'!$H$2:$H$995,E23) -> 1427 | H23: =SUMIFS('Sales Data'!$F$2:$F$995,'Sales Data'!$H$2:$H$995,E23) -> 635054000 | I23: =H23/SUM(H$22:H$38) -> 0.14240486 | J23: =IFERROR(H23/F23,0) -> 158763500
A24: Sport | B24: =COUNTIF(Products!$C$2:$C$51,A24) -> 4 | C24: =B24/SUM(B$22:B$38) -> 0.08 | E24: Naked Bike | F24: =COUNTIF(Products!$C$2:$C$51,E24) -> 7 | G24: =SUMIFS('Sales Data'!$E$2:$E$995,'Sales Data'!$H$2:$H$995,E24) -> 2150 | H24: =SUMIFS('Sales Data'!$F$2:$F$995,'Sales Data'!$H$2:$H$995,E24) -> 563310000 | I24: =H24/SUM(H$22:H$38) -> 0.12631694 | J24: =IFERROR(H24/F24,0) -> 80472857
A25: Adventure | B25: =COUNTIF(Products!$C$2:$C$51,A25) -> 4 | C25: =B25/SUM(B$22:B$38) -> 0.08 | E25: Heritage | F25: =COUNTIF(Products!$C$2:$C$51,E25) -> 2 | G25: =SUMIFS('Sales Data'!$E$2:$E$995,'Sales Data'!$H$2:$H$995,E25) -> 702 | H25: =SUMIFS('Sales Data'!$F$2:$F$995,'Sales Data'!$H$2:$H$995,E25) -> 553140000 | I25: =H25/SUM(H$22:H$38) -> 0.12403642 | J25: =IFERROR(H25/F25,0) -> 276570000
A26: Cruiser | B26: =COUNTIF(Products!$C$2:$C$51,A26) -> 4 | C26: =B26/SUM(B$22:B$38) -> 0.08 | E26: Adventure | F26: =COUNTIF(Products!$C$2:$C$51,E26) -> 4 | G26: =SUMIFS('Sales Data'!$E$2:$E$995,'Sales Data'!$H$2:$H$995,E26) -> 1556 | H26: =SUMIFS('Sales Data'!$F$2:$F$995,'Sales Data'!$H$2:$H$995,E26) -> 392804700 | I26: =H26/SUM(H$22:H$38) -> 0.088082741 | J26: =IFERROR(H26/F26,0) -> 98201175
A27: Underbone | B27: =COUNTIF(Products!$C$2:$C$51,A27) -> 3 | C27: =B27/SUM(B$22:B$38) -> 0.06 | E27: Sport | F27: =COUNTIF(Products!$C$2:$C$51,E27) -> 4 | G27: =SUMIFS('Sales Data'!$E$2:$E$995,'Sales Data'!$H$2:$H$995,E27) -> 1425 | H27: =SUMIFS('Sales Data'!$F$2:$F$995,'Sales Data'!$H$2:$H$995,E27) -> 372471000 | I27: =H27/SUM(H$22:H$38) -> 0.083523101 | J27: =IFERROR(H27/F27,0) -> 93117750
A28: Dual-Sport | B28: =COUNTIF(Products!$C$2:$C$51,A28) -> 3 | C28: =B28/SUM(B$22:B$38) -> 0.06 | E28: Dual-Sport | F28: =COUNTIF(Products!$C$2:$C$51,E28) -> 3 | G28: =SUMIFS('Sales Data'!$E$2:$E$995,'Sales Data'!$H$2:$H$995,E28) -> 1165 | H28: =SUMIFS('Sales Data'!$F$2:$F$995,'Sales Data'!$H$2:$H$995,E28) -> 306517800 | I28: =H28/SUM(H$22:H$38) -> 0.068733719 | J28: =IFERROR(H28/F28,0) -> 102172600
A29: Cafe Racer | B29: =COUNTIF(Products!$C$2:$C$51,A29) -> 2 | C29: =B29/SUM(B$22:B$38) -> 0.04 | E29: Cafe Racer | F29: =COUNTIF(Products!$C$2:$C$51,E29) -> 2 | G29: =SUMIFS('Sales Data'!$E$2:$E$995,'Sales Data'!$H$2:$H$995,E29) -> 578 | H29: =SUMIFS('Sales Data'!$F$2:$F$995,'Sales Data'!$H$2:$H$995,E29) -> 169052000 | I29: =H29/SUM(H$22:H$38) -> 0.037908313 | J29: =IFERROR(H29/F29,0) -> 84526000
A30: Commuter | B30: =COUNTIF(Products!$C$2:$C$51,A30) -> 2 | C30: =B30/SUM(B$22:B$38) -> 0.04 | E30: Touring | F30: =COUNTIF(Products!$C$2:$C$51,E30) -> 1 | G30: =SUMIFS('Sales Data'!$E$2:$E$995,'Sales Data'!$H$2:$H$995,E30) -> 427 | H30: =SUMIFS('Sales Data'!$F$2:$F$995,'Sales Data'!$H$2:$H$995,E30) -> 147315000 | I30: =H30/SUM(H$22:H$38) -> 0.033033996 | J30: =IFERROR(H30/F30,0) -> 147315000
A31: Heritage | B31: =COUNTIF(Products!$C$2:$C$51,A31) -> 2 | C31: =B31/SUM(B$22:B$38) -> 0.04 | E31: Classic | F31: =COUNTIF(Products!$C$2:$C$51,E31) -> 1 | G31: =SUMIFS('Sales Data'!$E$2:$E$995,'Sales Data'!$H$2:$H$995,E31) -> 458 | H31: =SUMIFS('Sales Data'!$F$2:$F$995,'Sales Data'!$H$2:$H$995,E31) -> 114500000 | I31: =H31/SUM(H$22:H$38) -> 0.025675543 | J31: =IFERROR(H31/F31,0) -> 114500000
A32: Classic | B32: =COUNTIF(Products!$C$2:$C$51,A32) -> 1 | C32: =B32/SUM(B$22:B$38) -> 0.02 | E32: Underbone | F32: =COUNTIF(Products!$C$2:$C$51,E32) -> 3 | G32: =SUMIFS('Sales Data'!$E$2:$E$995,'Sales Data'!$H$2:$H$995,E32) -> 812 | H32: =SUMIFS('Sales Data'!$F$2:$F$995,'Sales Data'!$H$2:$H$995,E32) -> 90240800 | I32: =H32/SUM(H$22:H$38) -> 0.020235646 | J32: =IFERROR(H32/F32,0) -> 30080267
A33: Retro | B33: =COUNTIF(Products!$C$2:$C$51,A33) -> 1 | C33: =B33/SUM(B$22:B$38) -> 0.02 | E33: Scrambler | F33: =COUNTIF(Products!$C$2:$C$51,E33) -> 1 | G33: =SUMIFS('Sales Data'!$E$2:$E$995,'Sales Data'!$H$2:$H$995,E33) -> 304 | H33: =SUMIFS('Sales Data'!$F$2:$F$995,'Sales Data'!$H$2:$H$995,E33) -> 89680000 | I33: =H33/SUM(H$22:H$38) -> 0.020109892 | J33: =IFERROR(H33/F33,0) -> 89680000
... A38: Street | B38: =COUNTIF(Products!$C$2:$C$51,A38) -> 1 | C38: =B38/SUM(B$22:B$38) -> 0.02 | E38: Standard | F38: =COUNTIF(Products!$C$2:$C$51,E38) -> 1 | G38: =SUMIFS('Sales Data'!$E$2:$E$995,'Sales Data'!$H$2:$H$995,E38) -> 395 | H38: =SUMIFS('Sales Data'!$F$2:$F$995,'Sales Data'!$H$2:$H$995,E38) -> 27215500 | I38: =H38/SUM(H$22:H$38) -> 0.0061028186 | J38: =IFERROR(H38/F38,0) -> 27215500

Sheet Products
A1: Product ID Number | B1: Product Name | C1: Product Type | D1: Unit Price | E1: Date of Manufacturing | F1: Date of Acquisition | G1: Units Sold | H1: Revenue
A2: 37 | B2: Moto Morini X-Cape 650 | C2: Adventure | D2: 369000 | E2: 2023 | F2: 2024 | G2: =SUMIFS('Sales Data'!$E$2:$E$995,'Sales Data'!$C$2:$C$995,B2) -> 297 | H2: =SUMIFS('Sales Data'!$F$2:$F$995,'Sales Data'!$C$2:$C$995,B2) -> 109593000
A3: 15 | B3: BMW G 310 GS | C3: Adventure | D3: 320000 | E3: 2023 | F3: 2024 | G3: =SUMIFS('Sales Data'!$E$2:$E$995,'Sales Data'!$C$2:$C$995,B3) -> 426 | H3: =SUMIFS('Sales Data'!$F$2:$F$995,'Sales Data'!$C$2:$C$995,B3) -> 136320000
A4: 33 | B4: Zontes 310X | C4: Adventure | D4: 248000 | E4: 2023 | F4: 2024 | G4: =SUMIFS('Sales Data'!$E$2:$E$995,'Sales Data'!$C$2:$C$995,B4) -> 480 | H4: =SUMIFS('Sales Data'!$F$2:$F$995,'Sales Data'!$C$2:$C$995,B4) -> 119040000
A5: 24 | B5: Motorstar Xplorer 250R | C5: Adventure | D5: 78900 | E5: 2020 | F5: 2021 | G5: =SUMIFS('Sales Data'!$E$2:$E$995,'Sales Data'!$C$2:$C$995,B5) -> 353 | H5: =SUMIFS('Sales Data'!$F$2:$F$995,'Sales Data'!$C$2:$C$995,B5) -> 27851700
A6: 7 | B6: Bristol Veloce 500 | C6: Cafe Racer | D6: 328000 | E6: 2022 | F6: 2023 | G6: =SUMIFS('Sales Data'!$E$2:$E$995,'Sales Data'!$C$2:$C$995,B6) -> 230 | H6: =SUMIFS('Sales Data'!$F$2:$F$995,'Sales Data'!$C$2:$C$995,B6) -> 75440000
A7: 48 | B7: Zontes GK350 | C7: Cafe Racer | D7: 269000 | E7: 2023 | F7: 2024 | G7: =SUMIFS('Sales Data'!$E$2:$E$995,'Sales Data'!$C$2:$C$995,B7) -> 348 | H7: =SUMIFS('Sales Data'!$F$2:$F$995,'Sales Data'!$C$2:$C$995,B7) -> 93612000
A8: 5 | B8: Royal Enfield Classic 350 | C8: Classic | D8: 250000 | E8: 2022 | F8: 2023 | G8: =SUMIFS('Sales Data'!$E$2:$E$995,'Sales Data'!$C$2:$C$995,B8) -> 458 | H8: =SUMIFS('Sales Data'!$F$2:$F$995,'Sales Data'!$C$2:$C$995,B8) -> 114500000
A9: 28 | B9: Bajaj CT125 | C9: Commuter | D9: 67900 | E9: 2021 | F9: 2022 | G9: =SUMIFS('Sales Data'!$E$2:$E$995,'Sales Data'!$C$2:$C$995,B9) -> 509 | H9: =SUMIFS('Sales Data'!$F$2:$F$995,'Sales Data'!$C$2:$C$995,B9) -> 34561100
A10: 30 | B10: Rusi Flash 125 | C10: Commuter | D10: 48000 | E10: 2020 | F10: 2021 | G10: =SUMIFS('Sales Data'!$E$2:$E$995,'Sales Data'!$C$2:$C$995,B10) -> 393 | H10: =SUMIFS('Sales Data'!$F$2:$F$995,'Sales Data'!$C$2:$C$995,B10) -> 18864000
A11: 42 | B11: Honda Rebel 1100 | C11: Cruiser | D11: 650000 | E11: 2023 | F11: 2024 | G11: =SUMIFS('Sales Data'!$E$2:$E$995,'Sales Data'!$C$2:$C$995,B11) -> 256 | H11: =SUMIFS('Sales Data'!$F$2:$F$995,'Sales Data'!$C$2:$C$995,B11) -> 166400000
A12: 32 | B12: Harley-Davidson Street 750 | C12: Cruiser | D12: 499000 | E12: 2020 | F12: 2021 | G12: =SUMIFS('Sales Data'!$E$2:$E$995,'Sales Data'!$C$2:$C$995,B12) -> 212 | H12: =SUMIFS('Sales Data'!$F$2:$F$995,'Sales Data'!$C$2:$C$995,B12) -> 105788000
A13: 22 | B13: Bristol Bobber 650 | C13: Cruiser | D13: 398000 | E13: 2022 | F13: 2023 | G13: =SUMIFS('Sales Data'!$E$2:$E$995,'Sales Data'!$C$2:$C$995,B13) -> 575 | H13: =SUMIFS('Sales Data'!$F$2:$F$995,'Sales Data'!$C$2:$C$995,B13) -> 228850000
... A51: 50 | B51: SYM Husky 150 | C51: Underbone | D51: 72900 | E51: 2022 | F51: 2023 | G51: =SUMIFS('Sales Data'!$E$2:$E$995,'Sales Data'!$C$2:$C$995,B51) -> 190 | H51: =SUMIFS('Sales Data'!$F$2:$F$995,'Sales Data'!$C$2:$C$995,B51) -> 13851000

Sheet Sales Data
A1: Date | B1: Client Type | C1: Product Name | D1: Unit Price | E1: Quantity | F1: Total | G1: Payment Method | H1: Product Type
A2: 45670 | B2: Retail | C2: Bajaj CT125 | D2: 67900 | E2: 21 | F2: =D2*E2 -> 1425900 | G2: Cash | H2: =INDEX(Products!$C$2:$C$51,MATCH(C2,Products!$B$2:$B$51,0)) -> Commuter
A3: 45809 | B3: Retail | C3: Vespa Primavera 150 | D3: 210000 | E3: 1 | F3: =D3*E3 -> 210000 | G3: Cash | H3: =INDEX(Products!$C$2:$C$51,MATCH(C3,Products!$B$2:$B$51,0)) -> Scooter
A4: 45809 | B4: Wholesale | C4: Keeway RKS 150 Sport | D4: 68900 | E4: 12 | F4: =D4*E4 -> 826800 | G4: Transfer | H4: =INDEX(Products!$C$2:$C$51,MATCH(C4,Products!$B$2:$B$51,0)) -> Standard
A5: 45809 | B5: Retail | C5: Honda CRF300L | D5: 284900 | E5: 32 | F5: =D5*E5 -> 9116800 | G5: Transfer | H5: =INDEX(Products!$C$2:$C$51,MATCH(C5,Products!$B$2:$B$51,0)) -> Dual-Sport
A6: 45809 | B6: Wholesale | C6: Suzuki Raider R150 Fi | D6: 119900 | E6: 3 | F6: =D6*E6 -> 359700 | G6: Credit Card | H6: =INDEX(Products!$C$2:$C$51,MATCH(C6,Products!$B$2:$B$51,0)) -> Underbone
A7: 45809 | B7: Wholesale | C7: Yamaha Aerox 155 | D7: 124000 | E7: 23 | F7: =D7*E7 -> 2852000 | G7: Transfer | H7: =INDEX(Products!$C$2:$C$51,MATCH(C7,Products!$B$2:$B$51,0)) -> Scooter
A8: 45809 | B8: Retail | C8: Keeway RKS 150 Sport | D8: 68900 | E8: 20 | F8: =D8*E8 -> 1378000 | G8: Transfer | H8: =INDEX(Products!$C$2:$C$51,MATCH(C8,Products!$B$2:$B$51,0)) -> Standard
A9: 45809 | B9: Wholesale | C9: KTM 790 Duke | D9: 599000 | E9: 9 | F9: =D9*E9 -> 5391000 | G9: Transfer | H9: =INDEX(Products!$C$2:$C$51,MATCH(C9,Products!$B$2:$B$51,0)) -> Naked Bike
A10: 45809 | B10: Retail | C10: Yamaha XMAX 300 | D10: 319000 | E10: 26 | F10: =D10*E10 -> 8294000 | G10: Transfer | H10: =INDEX(Products!$C$2:$C$51,MATCH(C10,Products!$B$2:$B$51,0)) -> Scooter
A11: 45809 | B11: Retail | C11: Suzuki GSX-S150 | D11: 125000 | E11: 13 | F11: =D11*E11 -> 1625000 | G11: Cash | H11: =INDEX(Products!$C$2:$C$51,MATCH(C11,Products!$B$2:$B$51,0)) -> Naked Bike
A12: 45809 | B12: Wholesale | C12: Moto Guzzi V7 Stone | D12: 689000 | E12: 12 | F12: =D12*E12 -> 8268000 | G12: Transfer | H12: =INDEX(Products!$C$2:$C$51,MATCH(C12,Products!$B$2:$B$51,0)) -> Heritage
A13: 45809 | B13: Retail | C13: Aprilia SR GT 200 | D13: 219000 | E13: 10 | F13: =D13*E13 -> 2190000 | G13: Cash | H13: =INDEX(Products!$C$2:$C$51,MATCH(C13,Products!$B$2:$B$51,0)) -> Scooter
... A995: 45900 | B995: Retail | C995: CFMoto 300NK | D995: 165000 | E995: 38 | F995: =D995*E995 -> 6270000 | G995: Credit Card | H995: =INDEX(Products!$C$2:$C$51,MATCH(C995,Products!$B$2:$B$51,0)) -> Naked Bike

Sheet Data Quality
A1: Data-quality checks run by the script
A3: Dataset | B3: Check | C3: Result
A4: Products | B4: Product rows loaded | C4: 50
A5: Products | B5: Products with blank name/category/price removed | C5: 0
A6: Products | B6: Duplicate product rows removed | C6: 0
A7: Products | B7: Duplicate Product IDs removed | C7: 0
A8: Products | B8: Category labels written in more than one way | C8: 0
A9: Products | B9: Duplicate Product Names (sales are matched on name) | C9: 0
A10: Products | B10: Product rows used | C10: 50
A11: Sales | B11: Sales rows loaded | C11: 994
A12: Sales | B12: Rows removed (missing/invalid date, product, price or quantity) | C12: 0
A13: Sales | B13: Blank Client Type labelled 'Unknown' | C13: 0
A14: Sales | B14: Client Type recorded as 'Unknown' (kept in totals) | C14: 10
A15: Sales | B15: Blank Payment Method labelled 'Unknown' | C15: 0
... A21: Sales | B21: Sales rows used | C21: 994
A23: Not covered: stock levels (not in the data), whether prices and quantities are true, and whether similar but different category names should be merged.
